CHANGELOG.txt
LICENCE.txt
MANIFEST.in
README.txt
setup.py
ConnectionValidation/__init__.py
ConnectionValidation.egg-info/PKG-INFO
ConnectionValidation.egg-info/SOURCES.txt
ConnectionValidation.egg-info/dependency_links.txt
ConnectionValidation.egg-info/top_level.txt
ConnectionValidation/pytransform/__init__.py