Metadata-Version: 1.1
Name: ConnectionValidation
Version: 0.4.7
Summary: Validad con un Dongle
Home-page: UNKNOWN
Author: Wilbert Sanchez
Author-email: wilbertenriquechable522@gmail.com
License: MIT
Keywords: Validador
Platform: UNKNOWN
Classifier: Development Status :: 5 - Production/Stable
Classifier: Intended Audience :: Education
Classifier: Operating System :: Microsoft :: Windows :: Windows 10
Classifier: License :: OSI Approved :: MIT License
Classifier: Programming Language :: Python :: 3
